subdomainfinder/__init__.py
subdomainfinder/__main__.py
subdomainfinder-1.2.dist-info/LICENSE
subdomainfinder-1.2.dist-info/METADATA
subdomainfinder-1.2.dist-info/WHEEL
subdomainfinder-1.2.dist-info/entry_points.txt
subdomainfinder-1.2.dist-info/top_level.txt
subdomainfinder-1.2.dist-info/RECORD
