Metadata-Version: 2.1
Name: subdomainfinder
Version: 1.2
Summary: A python based tool for finding subdomains of a domain.
Home-page: https://github.com/ankushbhagatofficial/subdomain-finder
Author: Ankush Bhagat
Author-email: <ankushbhagatofficial@gmail.com>
License: MIT
Keywords: python,SecurityTrails,API,findsubdomain
Platform: UNKNOWN
Classifier: Development Status :: 1 - Planning
Classifier: Programming Language :: Python :: 3
Classifier: Operating System :: Unix
Classifier: Operating System :: MacOS :: MacOS X
Classifier: Operating System :: Microsoft :: Windows
Requires-Dist: requests
Requires-Dist: rich
